certbot_dns_myonlineportal/__init__.py
certbot_dns_myonlineportal/dns_myonlineportal.py
certbot_dns_myonlineportal/dns_myonlineportal_test.py
certbot_dns_myonlineportal-0.1.0.dist-info/METADATA
certbot_dns_myonlineportal-0.1.0.dist-info/WHEEL
certbot_dns_myonlineportal-0.1.0.dist-info/entry_points.txt
certbot_dns_myonlineportal-0.1.0.dist-info/top_level.txt
certbot_dns_myonlineportal-0.1.0.dist-info/RECORD
